layint_scan_api/__init__.py
layint_scan_api/api_client.py
layint_scan_api/configuration.py
layint_scan_api/rest.py
layint_scan_api/apis/__init__.py
layint_scan_api/apis/analytics_api.py
layint_scan_api/apis/authentication_api.py
layint_scan_api/apis/clair_api.py
layint_scan_api/apis/compliance_api.py
layint_scan_api/apis/images_api.py
layint_scan_api/apis/license_api.py
layint_scan_api/apis/registry_api.py
layint_scan_api/apis/tags_api.py
layint_scan_api/models/__init__.py
layint_scan_api/models/bad_request_error.py
layint_scan_api/models/clair_data.py
layint_scan_api/models/clair_feature.py
layint_scan_api/models/clair_layer.py
layint_scan_api/models/clair_update_notification.py
layint_scan_api/models/clair_update_request.py
layint_scan_api/models/clair_vulnerability.py
layint_scan_api/models/compliance.py
layint_scan_api/models/compliance_result.py
layint_scan_api/models/compliances.py
layint_scan_api/models/cve_search.py
layint_scan_api/models/cve_search_data.py
layint_scan_api/models/cve_search_field.py
layint_scan_api/models/cve_search_image.py
layint_scan_api/models/ecr_credentials.py
layint_scan_api/models/image.py
layint_scan_api/models/image_log.py
layint_scan_api/models/image_logs.py
layint_scan_api/models/image_name.py
layint_scan_api/models/image_ref.py
layint_scan_api/models/images.py
layint_scan_api/models/inline_response_200.py
layint_scan_api/models/inline_response_200_1.py
layint_scan_api/models/license.py
layint_scan_api/models/license_product.py
layint_scan_api/models/license_request.py
layint_scan_api/models/license_runtime.py
layint_scan_api/models/license_scan.py
layint_scan_api/models/local_auth_request.py
layint_scan_api/models/package_search_data.py
layint_scan_api/models/package_search_result.py
layint_scan_api/models/package_search_results.py
layint_scan_api/models/package_version.py
layint_scan_api/models/policies.py
layint_scan_api/models/policy.py
layint_scan_api/models/policy_rule.py
layint_scan_api-0.9.6.dist-info/METADATA
layint_scan_api-0.9.6.dist-info/RECORD
layint_scan_api-0.9.6.dist-info/WHEEL
layint_scan_api-0.9.6.dist-info/top_level.txt
