Metadata-Version: 2.1
Name: layint-scan-api
Version: 0.9.6
Summary: Layered Insight Scan
Home-page: UNKNOWN
Author: UNKNOWN
Author-email: help@layeredinsight.com
License: UNKNOWN
Keywords: Swagger,Layered Insight Scan
Platform: UNKNOWN
Requires-Dist: urllib3 (>=1.15)
Requires-Dist: six (>=1.10)
Requires-Dist: certifi
Requires-Dist: python-dateutil
